README.md
setup.py
test/test_dense.py
test/test_lr.py
test/test_nms.py
test/test_ops.py
test/test_transforms.py
vlkit/__init__.py
vlkit/args.py
vlkit/detection.py
vlkit/imagenet_labels.py
vlkit/io.py
vlkit/semseg.py
vlkit/utils.py
vlkit.egg-info/PKG-INFO
vlkit.egg-info/SOURCES.txt
vlkit.egg-info/dependency_links.txt
vlkit.egg-info/not-zip-safe
vlkit.egg-info/requires.txt
vlkit.egg-info/top_level.txt
vlkit/data/imagenet1000_clsidx_to_labels.txt
vlkit/datasets/__init__.py
vlkit/datasets/datasets.py
vlkit/datasets/filelist.py
vlkit/dense/__init__.py
vlkit/dense/dense.py
vlkit/image/__init__.py
vlkit/image/image.py
vlkit/lrscheduler/__init__.py
vlkit/lrscheduler/base.py
vlkit/lrscheduler/cosine.py
vlkit/lrscheduler/step.py
vlkit/models/__init__.py
vlkit/models/transformer.py
vlkit/nms/__init__.py
vlkit/nms/_nms_ext.c
vlkit/nms/nms.h
vlkit/nms/nms_ext.c
vlkit/nms/nms_ext.pyx
vlkit/ops/__init__.py
vlkit/ops/blocks.py
vlkit/ops/conv.py
vlkit/ops/distributed.py
vlkit/ops/divergence.py
vlkit/ops/drop.py
vlkit/ops/dual_bn.py
vlkit/ops/nn.py
vlkit/ops/squeeze_excite.py
vlkit/pytorch/__init__.py
vlkit/pytorch/loss.py
vlkit/pytorch/wasserstein.py
vlkit/transforms/__init__.py
vlkit/transforms/interpolation.py
vlkit/transforms/resize.py
vlkit/transforms/transforms.py