Metadata-Version: 1.0
Name: vlkit
Version: 0.1.0b10
Summary: vision and learning kit
Home-page: https://github.com/vlkit/vlkit
Author: UNKNOWN
Author-email: kz@kaizhao.net
License: MIT
Platform: UNKNOWN
